nrdash/__init__.py
nrdash/main.py
nrdash/models.py
nrdash/new_relic_api.py
nrdash/parsing.py
nrdash-0.2.1.dist-info/LICENSE
nrdash-0.2.1.dist-info/METADATA
nrdash-0.2.1.dist-info/WHEEL
nrdash-0.2.1.dist-info/entry_points.txt
nrdash-0.2.1.dist-info/top_level.txt
nrdash-0.2.1.dist-info/RECORD
