Metadata-Version: 2.1
Name: nrdash
Version: 0.2.1
Summary: New Relic Dashboard Builder
Home-page: https://github.com/gatkin/nrdashboards
Author: Greg Atkin
Author-email: greg.scott.atkin@gmail.com
License: MIT
Platform: UNKNOWN
Classifier: Programming Language :: Python :: 3
Classifier: License :: OSI Approved :: MIT License
Requires-Python: >=3.6
Requires-Dist: pyyaml
Requires-Dist: attrs
Requires-Dist: typing
Requires-Dist: requests
Requires-Dist: click
